{
  "type": "minecraft:crafting_shaped",
  "category": "misc",
  "pattern": [
    "012",
    "345",
    "678"
  ],
  "key": {
    "0": {
      "item": "minecraft:golden_apple"
    },
    "1": {
      "item": "minecraft:iron_block"
    },
    "2": {
      "item": "minecraft:golden_apple"
    },
    "3": {
      "item": "minecraft:iron_block"
    },
    "4": {
      "item": "gems_fabric_mod:gem_crystal"
    },
    "5": {
      "item": "minecraft:iron_block"
    },
    "6": {
      "item": "minecraft:golden_apple"
    },
    "7": {
      "item": "minecraft:iron_block"
    },
    "8": {
      "item": "minecraft:golden_apple"
    }
  },
  "result": {
    "item": "minecraft:air",
    "count": 1
  }
}