{
  "_fv": 47,
  "_type": "tool",
  "definition": {
    "toolType": "Sword",
    "renderType": 0,
    "texture": "unnamed_3",
    "customModelName": "Normal",
    "name": "Netherite Gem Sword",
    "specialInfo": [
      "Given by the Netherite Gem"
    ],
    "creativeTab": {
      "value": "No creative tab entry"
    },
    "harvestLevel": 1,
    "efficiency": 4.0,
    "attackSpeed": 1.6,
    "enchantability": 0,
    "damageVsEntity": 14.0,
    "usageCount": 100,
    "blocksAffected": [],
    "hasGlow": false,
    "repairItems": [],
    "immuneToFire": true,
    "stayInGridWhenCrafting": false,
    "damageOnCrafting": false
  }
}